MANIFEST.in
setup.py
danemco_uploader.egg-info/PKG-INFO
danemco_uploader.egg-info/SOURCES.txt
danemco_uploader.egg-info/dependency_links.txt
danemco_uploader.egg-info/pbr.json
danemco_uploader.egg-info/requires.txt
danemco_uploader.egg-info/top_level.txt
uploader/__init__.py
uploader/admin.py
uploader/apps.py
uploader/models.py
uploader/settings.py
uploader/signals.py
uploader/urls.py
uploader/utils.py
uploader/views.py
uploader/fixtures/initial_data.json
uploader/migrations/0001_initial.py
uploader/migrations/__init__.py
uploader/static/uploader/css/all_files.css
uploader/static/uploader/js/tinymce_file_manager.js
uploader/templates/admin/uploader/imageupload/change_list.html
uploader/templates/uploader/all_files.html
uploader/templates/uploader/fileupload_list.html
uploader/templates/uploader/imageupload_list.html
uploader/templates/uploader/send_to_gallery.html
uploader/templatetags/__init__.py
uploader/templatetags/uploader_tags.py
uploader/tests/__init__.py
uploader/tests/test_admin_views.py
uploader/tests/test_signals.py
uploader/tests/test_views.py
uploader/tests/urls.py