Metadata-Version: 1.0
Name: danemco-uploader
Version: 1.2.0
Summary: A file and image uploader
Home-page: https://git.velocitywebworks.com/lib/danemco-uploader
Author: Danemco, LLC
Author-email: dev@velocitywebworks.com
License: UNKNOWN
Platform: UNKNOWN
